uie/LICENSE
uie/__init__.py
uie/convert.py
uie/doccano.md
uie/doccano.py
uie/ernie.py
uie/ernie_m.py
uie/evaluate.py
uie/export_model.py
uie/finetune.py
uie/labelstudio2doccano.py
uie/model.py
uie/tokenizer.py
uie/uie.py
uie/utils.py
torch4uie-2023.5.5.17.26.36.dist-info/METADATA
torch4uie-2023.5.5.17.26.36.dist-info/WHEEL
torch4uie-2023.5.5.17.26.36.dist-info/entry_points.txt
torch4uie-2023.5.5.17.26.36.dist-info/top_level.txt
torch4uie-2023.5.5.17.26.36.dist-info/RECORD
